<?xml version="1.0" encoding="utf-8" ?>
<dwsync>
<file name="Exception.php" server="www.dancewearrialto.com/dancewearrialto.com/html/" local="129112079800000000" remote="129165809420000000" />
<file name="Ntp.php" server="www.dancewearrialto.com/dancewearrialto.com/html/" local="129112079780000000" remote="129165809440000000" />
<file name="Protocol.php" server="www.dancewearrialto.com/dancewearrialto.com/html/" local="129112079800000000" remote="129165809460000000" />
<file name="Sntp.php" server="www.dancewearrialto.com/dancewearrialto.com/html/" local="129112079800000000" remote="129165809470000000" />
<file name="Exception.php" server="dancerialto.com//home/dr/dancerialto.com/html/" local="129112079800000000" remote="129304824860000000" />
<file name="Ntp.php" server="dancerialto.com//home/dr/dancerialto.com/html/" local="129112079780000000" remote="129304824870000000" />
<file name="Protocol.php" server="dancerialto.com//home/dr/dancerialto.com/html/" local="129112079800000000" remote="129304824870000000" />
<file name="Sntp.php" server="dancerialto.com//home/dr/dancerialto.com/html/" local="129112079800000000" remote="129304824870000000" />
</dwsync>