<?xml version="1.0" encoding="utf-8" ?>
<dwsync>
<file name="AndCondition.php" server="www.dancewearrialto.com/dancewearrialto.com/html/" local="128426976520000000" remote="129165785010000000" />
<file name="Condition.php" server="www.dancewearrialto.com/dancewearrialto.com/html/" local="128426976520000000" remote="129165785020000000" />
<file name="ConditionBase.php" server="www.dancewearrialto.com/dancewearrialto.com/html/" local="128426976520000000" remote="129165785020000000" />
<file name="ContainsCondition.php" server="www.dancewearrialto.com/dancewearrialto.com/html/" local="128426976520000000" remote="129165785020000000" />
<file name="EqualsCondition.php" server="www.dancewearrialto.com/dancewearrialto.com/html/" local="128426976520000000" remote="129165785020000000" />
<file name="IsFalseCondition.php" server="www.dancewearrialto.com/dancewearrialto.com/html/" local="128426976520000000" remote="129165785030000000" />
<file name="IsSetCondition.php" server="www.dancewearrialto.com/dancewearrialto.com/html/" local="128426976520000000" remote="129165785030000000" />
<file name="IsTrueCondition.php" server="www.dancewearrialto.com/dancewearrialto.com/html/" local="128426976520000000" remote="129165785030000000" />
<file name="NotCondition.php" server="www.dancewearrialto.com/dancewearrialto.com/html/" local="128426976520000000" remote="129165785040000000" />
<file name="OrCondition.php" server="www.dancewearrialto.com/dancewearrialto.com/html/" local="128426976520000000" remote="129165785040000000" />
<file name="OsCondition.php" server="www.dancewearrialto.com/dancewearrialto.com/html/" local="128426976520000000" remote="129165785040000000" />
<file name="ReferenceExistsCondition.php" server="www.dancewearrialto.com/dancewearrialto.com/html/" local="128426976520000000" remote="129165785040000000" />
<file name="AndCondition.php" server="dancerialto.com//home/dr/dancerialto.com/html/" local="128426976520000000" remote="129305967100000000" />
<file name="Condition.php" server="dancerialto.com//home/dr/dancerialto.com/html/" local="128426976520000000" remote="129305967100000000" />
<file name="ConditionBase.php" server="dancerialto.com//home/dr/dancerialto.com/html/" local="128426976520000000" remote="129305967100000000" />
<file name="ContainsCondition.php" server="dancerialto.com//home/dr/dancerialto.com/html/" local="128426976520000000" remote="129305967110000000" />
<file name="EqualsCondition.php" server="dancerialto.com//home/dr/dancerialto.com/html/" local="128426976520000000" remote="129305967110000000" />
<file name="IsFalseCondition.php" server="dancerialto.com//home/dr/dancerialto.com/html/" local="128426976520000000" remote="129305967110000000" />
<file name="IsSetCondition.php" server="dancerialto.com//home/dr/dancerialto.com/html/" local="128426976520000000" remote="129305967120000000" />
<file name="IsTrueCondition.php" server="dancerialto.com//home/dr/dancerialto.com/html/" local="128426976520000000" remote="129305967120000000" />
<file name="NotCondition.php" server="dancerialto.com//home/dr/dancerialto.com/html/" local="128426976520000000" remote="129305967120000000" />
<file name="OrCondition.php" server="dancerialto.com//home/dr/dancerialto.com/html/" local="128426976520000000" remote="129305967120000000" />
<file name="OsCondition.php" server="dancerialto.com//home/dr/dancerialto.com/html/" local="128426976520000000" remote="129305967120000000" />
<file name="ReferenceExistsCondition.php" server="dancerialto.com//home/dr/dancerialto.com/html/" local="128426976520000000" remote="129305967130000000" />
</dwsync>