<?xml version="1.0" encoding="utf-8" ?>
<dwsync>
<file name="Barcode.php" server="www.dancewearrialto.com/dancewearrialto.com/html/" local="128426976500000000" remote="129165787990000000" />
<file name="Color.php" server="www.dancewearrialto.com/dancewearrialto.com/html/" local="128426976500000000" remote="129165788000000000" />
<file name="GIS.php" server="www.dancewearrialto.com/dancewearrialto.com/html/" local="128426976500000000" remote="129165788000000000" />
<file name="GraphViz.php" server="www.dancewearrialto.com/dancewearrialto.com/html/" local="128426976500000000" remote="129165788000000000" />
<file name="IPTC.php" server="www.dancewearrialto.com/dancewearrialto.com/html/" local="128426976500000000" remote="129165788010000000" />
<file name="Remote.php" server="www.dancewearrialto.com/dancewearrialto.com/html/" local="128426976500000000" remote="129165788010000000" />
<file name="Barcode.php" server="dancerialto.com//home/dr/dancerialto.com/html/" local="128426976500000000" remote="129305984710000000" />
<file name="Color.php" server="dancerialto.com//home/dr/dancerialto.com/html/" local="128426976500000000" remote="129305984730000000" />
<file name="GIS.php" server="dancerialto.com//home/dr/dancerialto.com/html/" local="128426976500000000" remote="129305984740000000" />
<file name="GraphViz.php" server="dancerialto.com//home/dr/dancerialto.com/html/" local="128426976500000000" remote="129305984750000000" />
<file name="IPTC.php" server="dancerialto.com//home/dr/dancerialto.com/html/" local="128426976500000000" remote="129305984770000000" />
<file name="Remote.php" server="dancerialto.com//home/dr/dancerialto.com/html/" local="128426976500000000" remote="129305984790000000" />
</dwsync>