<?xml version="1.0" encoding="utf-8" ?>
<dwsync>
<file name="Document.php" server="www.dancewearrialto.com/dancewearrialto.com/html/" local="129112080400000000" remote="129165820080000000" />
<file name="Exception.php" server="www.dancewearrialto.com/dancewearrialto.com/html/" local="129112080380000000" remote="129165820130000000" />
<file name="Field.php" server="www.dancewearrialto.com/dancewearrialto.com/html/" local="129112080280000000" remote="129165820150000000" />
<file name="FSM.php" server="www.dancewearrialto.com/dancewearrialto.com/html/" local="129112080260000000" remote="129165820170000000" />
<file name="FSMAction.php" server="www.dancewearrialto.com/dancewearrialto.com/html/" local="129112080160000000" remote="129165820190000000" />
<file name="Interface.php" server="www.dancewearrialto.com/dancewearrialto.com/html/" local="129112080380000000" remote="129165820210000000" />
<file name="LockManager.php" server="www.dancewearrialto.com/dancewearrialto.com/html/" local="129112080260000000" remote="129165820230000000" />
<file name="MultiSearcher.php" server="www.dancewearrialto.com/dancewearrialto.com/html/" local="129112080260000000" remote="129165820250000000" />
<file name="PriorityQueue.php" server="www.dancewearrialto.com/dancewearrialto.com/html/" local="129112080280000000" remote="129165820270000000" />
<file name="Proxy.php" server="www.dancewearrialto.com/dancewearrialto.com/html/" local="129112080380000000" remote="129165820290000000" />
<file name="TermStreamsPriorityQueue.php" server="www.dancewearrialto.com/dancewearrialto.com/html/" local="129112080160000000" remote="129165820310000000" />
<file name="Document.php" server="dancerialto.com//home/dr/dancerialto.com/html/" local="129112080400000000" remote="129304826820000000" />
<file name="Exception.php" server="dancerialto.com//home/dr/dancerialto.com/html/" local="129112080380000000" remote="129304826820000000" />
<file name="FSM.php" server="dancerialto.com//home/dr/dancerialto.com/html/" local="129112080260000000" remote="129304826820000000" />
<file name="FSMAction.php" server="dancerialto.com//home/dr/dancerialto.com/html/" local="129112080160000000" remote="129304826830000000" />
<file name="Field.php" server="dancerialto.com//home/dr/dancerialto.com/html/" local="129112080280000000" remote="129304826830000000" />
<file name="Interface.php" server="dancerialto.com//home/dr/dancerialto.com/html/" local="129112080380000000" remote="129304826830000000" />
<file name="LockManager.php" server="dancerialto.com//home/dr/dancerialto.com/html/" local="129112080260000000" remote="129304826830000000" />
<file name="MultiSearcher.php" server="dancerialto.com//home/dr/dancerialto.com/html/" local="129112080260000000" remote="129304826840000000" />
<file name="PriorityQueue.php" server="dancerialto.com//home/dr/dancerialto.com/html/" local="129112080280000000" remote="129304826840000000" />
<file name="Proxy.php" server="dancerialto.com//home/dr/dancerialto.com/html/" local="129112080380000000" remote="129304826840000000" />
<file name="TermStreamsPriorityQueue.php" server="dancerialto.com//home/dr/dancerialto.com/html/" local="129112080160000000" remote="129304826850000000" />
</dwsync>