<?xml version="1.0" encoding="utf-8" ?>
<dwsync>
<file name="Abstract.php" server="www.dancewearrialto.com/dancewearrialto.com/html/" local="129112077800000000" remote="129165864590000000" />
<file name="Cli.php" server="www.dancewearrialto.com/dancewearrialto.com/html/" local="129112077800000000" remote="129165864610000000" />
<file name="Exception.php" server="www.dancewearrialto.com/dancewearrialto.com/html/" local="129112077800000000" remote="129165864630000000" />
<file name="Http.php" server="www.dancewearrialto.com/dancewearrialto.com/html/" local="129112077800000000" remote="129165864640000000" />
<file name="HttpTestCase.php" server="www.dancewearrialto.com/dancewearrialto.com/html/" local="129112077800000000" remote="129165864660000000" />
<file name="Abstract.php" server="dancerialto.com//home/dr/dancerialto.com/html/" local="129112077800000000" remote="129306048640000000" />
<file name="Cli.php" server="dancerialto.com//home/dr/dancerialto.com/html/" local="129112077800000000" remote="129306048660000000" />
<file name="Exception.php" server="dancerialto.com//home/dr/dancerialto.com/html/" local="129112077800000000" remote="129306048670000000" />
<file name="Http.php" server="dancerialto.com//home/dr/dancerialto.com/html/" local="129112077800000000" remote="129306048690000000" />
<file name="HttpTestCase.php" server="dancerialto.com//home/dr/dancerialto.com/html/" local="129112077800000000" remote="129306048710000000" />
</dwsync>